{
  "version": "7",
  "dialect": "postgresql",
  "entries": [
    {
      "idx": 0,
      "version": "7",
      "when": 1735360341600,
      "tag": "0000_amusing_the_call",
      "breakpoints": true
    },
    {
      "idx": 1,
      "version": "7",
      "when": 1735485675727,
      "tag": "0001_lumpy_gabe_jones",
      "breakpoints": true
    },
    {
      "idx": 2,
      "version": "7",
      "when": 1735486504620,
      "tag": "0002_abandoned_stingray",
      "breakpoints": true
    }
  ]
}